athenanews/__init__.py
athenanews/news.py
athenanewsapi-0.1.3.dist-info/licenses/LICENSE
athenanewsapi-0.1.3.dist-info/METADATA
athenanewsapi-0.1.3.dist-info/WHEEL
athenanewsapi-0.1.3.dist-info/top_level.txt
athenanewsapi-0.1.3.dist-info/RECORD
