Metadata-Version: 2.4
Name: athenanewsapi
Version: 0.1.3
Summary: A simple wrapper for the Athena News API to simplify searching for articles.
Home-page: https://github.com/athenanewsapi/athenanews
Author: Matt F.
Author-email: matt@runathena.com
Classifier: Programming Language :: Python :: 3
Classifier: License :: OSI Approved :: MIT License
Classifier: Operating System :: OS Independent
Requires-Python: >=3.6
License-File: LICENSE
Requires-Dist: requests
Dynamic: author
Dynamic: author-email
Dynamic: classifier
Dynamic: description
Dynamic: description-content-type
Dynamic: home-page
Dynamic: license-file
Dynamic: requires-dist
Dynamic: requires-python
Dynamic: summary
